[
{ "seq_id" : 0, "qsl_idx" : 19161, "data" : "00005243" },
{ "seq_id" : 1, "qsl_idx" : 40983, "data" : "00C05B44" },
{ "seq_id" : 2, "qsl_idx" : 16982, "data" : "00403244" },
{ "seq_id" : 3, "qsl_idx" : 24142, "data" : "00803844" },
{ "seq_id" : 4, "qsl_idx" : 45105, "data" : "00800344" },
{ "seq_id" : 5, "qsl_idx" : 1599, "data" : "0000F643" },
{ "seq_id" : 6, "qsl_idx" : 28870, "data" : "00007744" },
{ "seq_id" : 7, "qsl_idx" : 26552, "data" : "00C05F44" },
{ "seq_id" : 8, "qsl_idx" : 31823, "data" : "0000B842" },
{ "seq_id" : 9, "qsl_idx" : 42160, "data" : "00C07344" },
{ "seq_id" : 10, "qsl_idx" : 2695, "data" : "00804B44" },
{ "seq_id" : 11, "qsl_idx" : 7256, "data" : "0000D041" },
{ "seq_id" : 12, "qsl_idx" : 22166, "data" : "00407744" },
{ "seq_id" : 13, "qsl_idx" : 45452, "data" : "00808643" },
{ "seq_id" : 14, "qsl_idx" : 1844, "data" : "0080E743" },
{ "seq_id" : 15, "qsl_idx" : 36071, "data" : "00007E43" },
{ "seq_id" : 16, "qsl_idx" : 38474, "data" : "0080C343" },
{ "seq_id" : 17, "qsl_idx" : 18999, "data" : "00003C44" },
{ "seq_id" : 18, "qsl_idx" : 12964, "data" : "00403144" },
{ "seq_id" : 19, "qsl_idx" : 26396, "data" : "00000000" },
{ "seq_id" : 20, "qsl_idx" : 47142, "data" : "00403944" },
{ "seq_id" : 21, "qsl_idx" : 42584, "data" : "00800444" },
{ "seq_id" : 22, "qsl_idx" : 2318, "data" : "00007743" },
{ "seq_id" : 23, "qsl_idx" : 42678, "data" : "0000B442" },
{ "seq_id" : 24, "qsl_idx" : 31456, "data" : "0080E043" },
{ "seq_id" : 25, "qsl_idx" : 20531, "data" : "00800544" },
{ "seq_id" : 26, "qsl_idx" : 35638, "data" : "00406A44" },
{ "seq_id" : 27, "qsl_idx" : 12202, "data" : "00006B43" },
{ "seq_id" : 28, "qsl_idx" : 32212, "data" : "00804644" },
{ "seq_id" : 29, "qsl_idx" : 2502, "data" : "00002543" },
{ "seq_id" : 30, "qsl_idx" : 5395, "data" : "00002844" },
{ "seq_id" : 31, "qsl_idx" : 7276, "data" : "00001744" },
{ "seq_id" : 32, "qsl_idx" : 2173, "data" : "00001F44" },
{ "seq_id" : 33, "qsl_idx" : 24005, "data" : "00405944" },
{ "seq_id" : 34, "qsl_idx" : 3781, "data" : "0080DC43" },
{ "seq_id" : 35, "qsl_idx" : 30040, "data" : "0000E642" },
{ "seq_id" : 36, "qsl_idx" : 41797, "data" : "00C07944" },
{ "seq_id" : 37, "qsl_idx" : 21529, "data" : "00002144" },
{ "seq_id" : 38, "qsl_idx" : 40813, "data" : "0080A143" },
{ "seq_id" : 39, "qsl_idx" : 17136, "data" : "0000EE42" },
{ "seq_id" : 40, "qsl_idx" : 35605, "data" : "00008A42" },
{ "seq_id" : 41, "qsl_idx" : 13700, "data" : "00003944" },
{ "seq_id" : 42, "qsl_idx" : 41366, "data" : "00806544" },
{ "seq_id" : 43, "qsl_idx" : 3784, "data" : "00005C42" },
{ "seq_id" : 44, "qsl_idx" : 23448, "data" : "0080A543" },
{ "seq_id" : 45, "qsl_idx" : 9510, "data" : "0080BE43" },
{ "seq_id" : 46, "qsl_idx" : 19218, "data" : "00005F43" },
{ "seq_id" : 47, "qsl_idx" : 18682, "data" : "00C07444" },
{ "seq_id" : 48, "qsl_idx" : 10875, "data" : "0080C743" },
{ "seq_id" : 49, "qsl_idx" : 44496, "data" : "00802444" },
{ "seq_id" : 50, "qsl_idx" : 49892, "data" : "00006F43" },
{ "seq_id" : 51, "qsl_idx" : 5707, "data" : "00001842" },
{ "seq_id" : 52, "qsl_idx" : 40111, "data" : "00C05744" },
{ "seq_id" : 53, "qsl_idx" : 22662, "data" : "00807844" },
{ "seq_id" : 54, "qsl_idx" : 43339, "data" : "00802044" },
{ "seq_id" : 55, "qsl_idx" : 32733, "data" : "00001144" },
{ "seq_id" : 56, "qsl_idx" : 2314, "data" : "00005943" },
{ "seq_id" : 57, "qsl_idx" : 38239, "data" : "00C04F44" },
{ "seq_id" : 58, "qsl_idx" : 2133, "data" : "00803644" },
{ "seq_id" : 59, "qsl_idx" : 31227, "data" : "00402A44" },
{ "seq_id" : 60, "qsl_idx" : 8496, "data" : "00005C44" },
{ "seq_id" : 61, "qsl_idx" : 32500, "data" : "00007744" },
{ "seq_id" : 62, "qsl_idx" : 48706, "data" : "00805044" },
{ "seq_id" : 63, "qsl_idx" : 5599, "data" : "00C07244" },
{ "seq_id" : 288, "qsl_idx" : 25880, "data" : "00806744" },
{ "seq_id" : 289, "qsl_idx" : 34809, "data" : "0000F943" },
{ "seq_id" : 290, "qsl_idx" : 43610, "data" : "00806844" },
{ "seq_id" : 291, "qsl_idx" : 33535, "data" : "00400644" },
{ "seq_id" : 292, "qsl_idx" : 16142, "data" : "0000C643" },
{ "seq_id" : 293, "qsl_idx" : 35968, "data" :

...

202, "data" : "00803A44" },
{ "seq_id" : 49950, "qsl_idx" : 44658, "data" : "00001C42" },
{ "seq_id" : 49951, "qsl_idx" : 9751, "data" : "0000C842" },
{ "seq_id" : 49824, "qsl_idx" : 48844, "data" : "00403E44" },
{ "seq_id" : 49825, "qsl_idx" : 31988, "data" : "0080BC43" },
{ "seq_id" : 49826, "qsl_idx" : 36811, "data" : "00009841" },
{ "seq_id" : 49827, "qsl_idx" : 38350, "data" : "00404144" },
{ "seq_id" : 49828, "qsl_idx" : 2014, "data" : "00400344" },
{ "seq_id" : 49829, "qsl_idx" : 43280, "data" : "00007743" },
{ "seq_id" : 49830, "qsl_idx" : 2255, "data" : "00400D44" },
{ "seq_id" : 49831, "qsl_idx" : 17209, "data" : "00007944" },
{ "seq_id" : 49832, "qsl_idx" : 6969, "data" : "00006943" },
{ "seq_id" : 49833, "qsl_idx" : 22334, "data" : "00001043" },
{ "seq_id" : 49834, "qsl_idx" : 34378, "data" : "00008A43" },
{ "seq_id" : 49835, "qsl_idx" : 28213, "data" : "00007843" },
{ "seq_id" : 49836, "qsl_idx" : 22315, "data" : "00004E44" },
{ "seq_id" : 49837, "qsl_idx" : 15807, "data" : "00005043" },
{ "seq_id" : 49838, "qsl_idx" : 17611, "data" : "0000CE43" },
{ "seq_id" : 49839, "qsl_idx" : 8015, "data" : "0080F343" },
{ "seq_id" : 49840, "qsl_idx" : 49196, "data" : "00003944" },
{ "seq_id" : 49841, "qsl_idx" : 24697, "data" : "00405044" },
{ "seq_id" : 49842, "qsl_idx" : 47061, "data" : "00008043" },
{ "seq_id" : 49843, "qsl_idx" : 20116, "data" : "00C00344" },
{ "seq_id" : 49844, "qsl_idx" : 12050, "data" : "00804744" },
{ "seq_id" : 49845, "qsl_idx" : 6496, "data" : "00401A44" },
{ "seq_id" : 49846, "qsl_idx" : 4325, "data" : "00005744" },
{ "seq_id" : 49847, "qsl_idx" : 8501, "data" : "00003743" },
{ "seq_id" : 49848, "qsl_idx" : 7847, "data" : "00001F44" },
{ "seq_id" : 49849, "qsl_idx" : 41664, "data" : "0080B543" },
{ "seq_id" : 49850, "qsl_idx" : 944, "data" : "0000BA43" },
{ "seq_id" : 49851, "qsl_idx" : 34481, "data" : "00007041" },
{ "seq_id" : 49852, "qsl_idx" : 47237, "data" : "00005442" },
{ "seq_id" : 49853, "qsl_idx" : 15220, "data" : "00008442" },
{ "seq_id" : 49854, "qsl_idx" : 89, "data" : "00004842" },
{ "seq_id" : 49855, "qsl_idx" : 35742, "data" : "00002644" },
{ "seq_id" : 49952, "qsl_idx" : 21894, "data" : "0000C543" },
{ "seq_id" : 49953, "qsl_idx" : 5653, "data" : "00C03C44" },
{ "seq_id" : 49954, "qsl_idx" : 35625, "data" : "00403944" },
{ "seq_id" : 49955, "qsl_idx" : 28704, "data" : "00407844" },
{ "seq_id" : 49956, "qsl_idx" : 5592, "data" : "00C06B44" },
{ "seq_id" : 49957, "qsl_idx" : 6750, "data" : "00008242" },
{ "seq_id" : 49958, "qsl_idx" : 27137, "data" : "00404244" },
{ "seq_id" : 49959, "qsl_idx" : 1273, "data" : "00003041" },
{ "seq_id" : 49960, "qsl_idx" : 39722, "data" : "00005844" },
{ "seq_id" : 49961, "qsl_idx" : 27328, "data" : "0080DC43" },
{ "seq_id" : 49962, "qsl_idx" : 35675, "data" : "00007543" },
{ "seq_id" : 49963, "qsl_idx" : 33504, "data" : "0000AB43" },
{ "seq_id" : 49964, "qsl_idx" : 36227, "data" : "00403144" },
{ "seq_id" : 49965, "qsl_idx" : 17881, "data" : "0000F841" },
{ "seq_id" : 49966, "qsl_idx" : 11147, "data" : "00805A44" },
{ "seq_id" : 49967, "qsl_idx" : 12938, "data" : "00006041" },
{ "seq_id" : 49968, "qsl_idx" : 6561, "data" : "0000C842" },
{ "seq_id" : 49969, "qsl_idx" : 6023, "data" : "00009543" },
{ "seq_id" : 49970, "qsl_idx" : 14936, "data" : "00804744" },
{ "seq_id" : 49971, "qsl_idx" : 39159, "data" : "00005244" },
{ "seq_id" : 49972, "qsl_idx" : 9769, "data" : "00402744" },
{ "seq_id" : 49973, "qsl_idx" : 37200, "data" : "00C03444" },
{ "seq_id" : 49974, "qsl_idx" : 47566, "data" : "00C06D44" },
{ "seq_id" : 49975, "qsl_idx" : 5088, "data" : "00809D43" },
{ "seq_id" : 49976, "qsl_idx" : 47668, "data" : "00001043" },
{ "seq_id" : 49977, "qsl_idx" : 1482, "data" : "00007044" },
{ "seq_id" : 49978, "qsl_idx" : 28212, "data" : "00008E43" },
{ "seq_id" : 49979, "qsl_idx" : 49664, "data" : "0000B841" },
{ "seq_id" : 49980, "qsl_idx" : 10764, "data" : "00003743" },
{ "seq_id" : 49981, "qsl_idx" : 534, "data" : "00804F44" },
{ "seq_id" : 49982, "qsl_idx" : 48177, "data" : "00008041" },
{ "seq_id" : 49983, "qsl_idx" : 32429, "data" : "00005244" }
]
