[
{ "seq_id" : 192, "qsl_idx" : 47409, "data" : "96010000" },
{ "seq_id" : 193, "qsl_idx" : 13386, "data" : "00010000" },
{ "seq_id" : 194, "qsl_idx" : 40026, "data" : "BC010000" },
{ "seq_id" : 195, "qsl_idx" : 3767, "data" : "3B000000" },
{ "seq_id" : 196, "qsl_idx" : 13968, "data" : "4F030000" },
{ "seq_id" : 197, "qsl_idx" : 7571, "data" : "E5030000" },
{ "seq_id" : 198, "qsl_idx" : 5844, "data" : "4C010000" },
{ "seq_id" : 199, "qsl_idx" : 17281, "data" : "45020000" },
{ "seq_id" : 200, "qsl_idx" : 2770, "data" : "4D020000" },
{ "seq_id" : 201, "qsl_idx" : 47329, "data" : "DA020000" },
{ "seq_id" : 202, "qsl_idx" : 21356, "data" : "A6000000" },
{ "seq_id" : 203, "qsl_idx" : 35054, "data" : "D3000000" },
{ "seq_id" : 204, "qsl_idx" : 764, "data" : "DC020000" },
{ "seq_id" : 205, "qsl_idx" : 28568, "data" : "36030000" },
{ "seq_id" : 206, "qsl_idx" : 18633, "data" : "37010000" },
{ "seq_id" : 207, "qsl_idx" : 18347, "data" : "22030000" },
{ "seq_id" : 208, "qsl_idx" : 49556, "data" : "8A020000" },
{ "seq_id" : 209, "qsl_idx" : 8775, "data" : "D0020000" },
{ "seq_id" : 210, "qsl_idx" : 28007, "data" : "6E020000" },
{ "seq_id" : 211, "qsl_idx" : 33303, "data" : "FE020000" },
{ "seq_id" : 212, "qsl_idx" : 3038, "data" : "49030000" },
{ "seq_id" : 213, "qsl_idx" : 6794, "data" : "DD010000" },
{ "seq_id" : 214, "qsl_idx" : 23931, "data" : "19000000" },
{ "seq_id" : 215, "qsl_idx" : 30892, "data" : "E5000000" },
{ "seq_id" : 216, "qsl_idx" : 47949, "data" : "AA000000" },
{ "seq_id" : 217, "qsl_idx" : 34685, "data" : "24010000" },
{ "seq_id" : 218, "qsl_idx" : 11714, "data" : "8E020000" },
{ "seq_id" : 219, "qsl_idx" : 24558, "data" : "17030000" },
{ "seq_id" : 220, "qsl_idx" : 8617, "data" : "30000000" },
{ "seq_id" : 221, "qsl_idx" : 22023, "data" : "99020000" },
{ "seq_id" : 222, "qsl_idx" : 30368, "data" : "8F010000" },
{ "seq_id" : 223, "qsl_idx" : 28495, "data" : "5B010000" },
{ "seq_id" : 224, "qsl_idx" : 5635, "data" : "4A010000" },
{ "seq_id" : 225, "qsl_idx" : 47493, "data" : "53010000" },
{ "seq_id" : 226, "qsl_idx" : 3835, "data" : "F6000000" },
{ "seq_id" : 227, "qsl_idx" : 10116, "data" : "0B030000" },
{ "seq_id" : 228, "qsl_idx" : 35434, "data" : "F0010000" },
{ "seq_id" : 229, "qsl_idx" : 5626, "data" : "1B010000" },
{ "seq_id" : 230, "qsl_idx" : 32420, "data" : "72000000" },
{ "seq_id" : 231, "qsl_idx" : 33624, "data" : "17010000" },
{ "seq_id" : 232, "qsl_idx" : 11875, "data" : "E0010000" },
{ "seq_id" : 233, "qsl_idx" : 37427, "data" : "E8000000" },
{ "seq_id" : 234, "qsl_idx" : 18998, "data" : "E3010000" },
{ "seq_id" : 235, "qsl_idx" : 19841, "data" : "34010000" },
{ "seq_id" : 236, "qsl_idx" : 36495, "data" : "DD010000" },
{ "seq_id" : 237, "qsl_idx" : 1069, "data" : "D2000000" },
{ "seq_id" : 238, "qsl_idx" : 19631, "data" : "B9020000" },
{ "seq_id" : 239, "qsl_idx" : 20762, "data" : "A7010000" },
{ "seq_id" : 240, "qsl_idx" : 17806, "data" : "92000000" },
{ "seq_id" : 241, "qsl_idx" : 38266, "data" : "A9030000" },
{ "seq_id" : 242, "qsl_idx" : 41625, "data" : "31030000" },
{ "seq_id" : 243, "qsl_idx" : 24340, "data" : "3E000000" },
{ "seq_id" : 244, "qsl_idx" : 30114, "data" : "14010000" },
{ "seq_id" : 245, "qsl_idx" : 15694, "data" : "C4010000" },
{ "seq_id" : 246, "qsl_idx" : 40749, "data" : "4D010000" },
{ "seq_id" : 247, "qsl_idx" : 15827, "data" : "99030000" },
{ "seq_id" : 248, "qsl_idx" : 34756, "data" : "49010000" },
{ "seq_id" : 249, "qsl_idx" : 38637, "data" : "5B000000" },
{ "seq_id" : 250, "qsl_idx" : 47580, "data" : "C2020000" },
{ "seq_id" : 251, "qsl_idx" : 36160, "data" : "8F020000" },
{ "seq_id" : 252, "qsl_idx" : 21089, "data" : "52000000" },
{ "seq_id" : 253, "qsl_idx" : 21858, "data" : "F7010000" },
{ "seq_id" : 254, "qsl_idx" : 946, "data" : "AF010000" },
{ "seq_id" : 255, "qsl_idx" : 38179, "data" : "45000000" },
{ "seq_id" : 704, "qsl_idx" : 16167, "data" : "02000000" },
{ "seq_id" : 705, "qsl_idx" : 32405, "data" : "F3000000" },
{ "seq_id" : 706, "qsl_idx" : 6690, "data" : "99020000" },
{ "seq_id" : 707, "qsl_idx" : 21062, "data" : "15000000" },
{ "seq_id" : 708, "qsl_idx" : 2

...

 "2F020000" },
{ "seq_id" : 49598, "qsl_idx" : 13366, "data" : "0C000000" },
{ "seq_id" : 49599, "qsl_idx" : 49274, "data" : "14030000" },
{ "seq_id" : 49600, "qsl_idx" : 33827, "data" : "95020000" },
{ "seq_id" : 49601, "qsl_idx" : 39009, "data" : "A4000000" },
{ "seq_id" : 49602, "qsl_idx" : 20101, "data" : "F9010000" },
{ "seq_id" : 49603, "qsl_idx" : 42866, "data" : "A5010000" },
{ "seq_id" : 49604, "qsl_idx" : 32599, "data" : "D8010000" },
{ "seq_id" : 49605, "qsl_idx" : 32631, "data" : "BF010000" },
{ "seq_id" : 49606, "qsl_idx" : 48184, "data" : "20030000" },
{ "seq_id" : 49607, "qsl_idx" : 45524, "data" : "3E010000" },
{ "seq_id" : 49608, "qsl_idx" : 9418, "data" : "5B000000" },
{ "seq_id" : 49609, "qsl_idx" : 37443, "data" : "BA010000" },
{ "seq_id" : 49610, "qsl_idx" : 1879, "data" : "E6030000" },
{ "seq_id" : 49611, "qsl_idx" : 112, "data" : "E3000000" },
{ "seq_id" : 49612, "qsl_idx" : 37668, "data" : "97000000" },
{ "seq_id" : 49613, "qsl_idx" : 15783, "data" : "21020000" },
{ "seq_id" : 49614, "qsl_idx" : 22456, "data" : "04030000" },
{ "seq_id" : 49615, "qsl_idx" : 25648, "data" : "C7000000" },
{ "seq_id" : 49616, "qsl_idx" : 19061, "data" : "67020000" },
{ "seq_id" : 49617, "qsl_idx" : 7784, "data" : "9B030000" },
{ "seq_id" : 49618, "qsl_idx" : 39759, "data" : "FA010000" },
{ "seq_id" : 49619, "qsl_idx" : 30104, "data" : "E0010000" },
{ "seq_id" : 49620, "qsl_idx" : 49303, "data" : "A2020000" },
{ "seq_id" : 49621, "qsl_idx" : 23284, "data" : "AC000000" },
{ "seq_id" : 49622, "qsl_idx" : 17520, "data" : "5F030000" },
{ "seq_id" : 49623, "qsl_idx" : 10896, "data" : "9B010000" },
{ "seq_id" : 49624, "qsl_idx" : 29558, "data" : "9D020000" },
{ "seq_id" : 49625, "qsl_idx" : 40836, "data" : "3C030000" },
{ "seq_id" : 49626, "qsl_idx" : 30377, "data" : "D9010000" },
{ "seq_id" : 49627, "qsl_idx" : 6938, "data" : "A9030000" },
{ "seq_id" : 49628, "qsl_idx" : 49914, "data" : "80010000" },
{ "seq_id" : 49629, "qsl_idx" : 1056, "data" : "6D000000" },
{ "seq_id" : 49630, "qsl_idx" : 25108, "data" : "2A030000" },
{ "seq_id" : 49631, "qsl_idx" : 40634, "data" : "A1020000" },
{ "seq_id" : 49632, "qsl_idx" : 47374, "data" : "76010000" },
{ "seq_id" : 49633, "qsl_idx" : 45102, "data" : "65000000" },
{ "seq_id" : 49634, "qsl_idx" : 7981, "data" : "E9010000" },
{ "seq_id" : 49635, "qsl_idx" : 23227, "data" : "24010000" },
{ "seq_id" : 49636, "qsl_idx" : 30805, "data" : "56010000" },
{ "seq_id" : 49637, "qsl_idx" : 19849, "data" : "91030000" },
{ "seq_id" : 49638, "qsl_idx" : 26526, "data" : "4B020000" },
{ "seq_id" : 49639, "qsl_idx" : 16662, "data" : "33030000" },
{ "seq_id" : 49640, "qsl_idx" : 17026, "data" : "7A020000" },
{ "seq_id" : 49641, "qsl_idx" : 15583, "data" : "EA010000" },
{ "seq_id" : 49642, "qsl_idx" : 46885, "data" : "DF020000" },
{ "seq_id" : 49643, "qsl_idx" : 31184, "data" : "FA000000" },
{ "seq_id" : 49644, "qsl_idx" : 15095, "data" : "CC000000" },
{ "seq_id" : 49645, "qsl_idx" : 37656, "data" : "A8010000" },
{ "seq_id" : 49646, "qsl_idx" : 31978, "data" : "C3020000" },
{ "seq_id" : 49647, "qsl_idx" : 15292, "data" : "2E010000" },
{ "seq_id" : 49648, "qsl_idx" : 45733, "data" : "F4000000" },
{ "seq_id" : 49649, "qsl_idx" : 29389, "data" : "9C020000" },
{ "seq_id" : 49650, "qsl_idx" : 47639, "data" : "BC030000" },
{ "seq_id" : 49651, "qsl_idx" : 2728, "data" : "9D010000" },
{ "seq_id" : 49652, "qsl_idx" : 47442, "data" : "FE010000" },
{ "seq_id" : 49653, "qsl_idx" : 23605, "data" : "AF030000" },
{ "seq_id" : 49654, "qsl_idx" : 22566, "data" : "D7020000" },
{ "seq_id" : 49655, "qsl_idx" : 41740, "data" : "CA030000" },
{ "seq_id" : 49656, "qsl_idx" : 33962, "data" : "BF000000" },
{ "seq_id" : 49657, "qsl_idx" : 33473, "data" : "66010000" },
{ "seq_id" : 49658, "qsl_idx" : 4433, "data" : "AD000000" },
{ "seq_id" : 49659, "qsl_idx" : 34614, "data" : "EC010000" },
{ "seq_id" : 49660, "qsl_idx" : 49953, "data" : "31000000" },
{ "seq_id" : 49661, "qsl_idx" : 1416, "data" : "C4010000" },
{ "seq_id" : 49662, "qsl_idx" : 7034, "data" : "2A000000" },
{ "seq_id" : 49663, "qsl_idx" : 19850, "data" : "A9030000" }
]
